Pydung-0.1.2.dist-info/METADATA
Pydung-0.1.2.dist-info/RECORD
Pydung-0.1.2.dist-info/WHEEL
Pydung-0.1.2.dist-info/top_level.txt
pydung/__init__.py
pydung/__main__.py
pydung/environment.py
