Metadata-Version: 2.1
Name: Pydung
Version: 0.1.2
Summary: An experimental, 3D terminal game. 'Nuff said.
Home-page: UNKNOWN
Author: Gustavo6046
Author-email: gugurehermann@gmail.com
License: MIT
Keywords: terminal 3d game experiment
Platform: UNKNOWN
